src/clock_gating_cell.v
// clock_gating_cell.v
// Standard latch-based Integrated Clock Gating (ICG) cell.
// Level-sensitive (not edge-triggered) latch avoids glitches on
// gated_clk that a plain combinational AND-gate approach would cause.
module clock_gating_cell (
    input  wire clk,       // Global (ungated) clock
    input  wire en,        // Functional enable
    input  wire test_en,   // DFT test-mode enable (bypasses gating in scan mode)
    output wire gated_clk
);

    reg en_latch;

    // FIX: use a BLOCKING assignment ('=') inside a latch description.
    // Non-blocking ('<=') in a level-sensitive latch is a well-known
    // synthesis/simulation style pitfall (can create race conditions
    // when multiple latches are evaluated on the same event, and some
    // synthesis tools warn/refuse to infer a clean latch from it).
    always @(clk or en or test_en) begin
        if (!clk)
            en_latch = en | test_en;
    end

    assign gated_clk = clk & en_latch;

endmodule

mac_clock_gating/mac_clock_gating.srcs/sources_1/imports/src/mac_unit_pipelined_cg.v
// mac_unit_pipelined_cg.v
//
// ADVANCED variant of the MAC unit. Two low-power techniques beyond the
// simple single-stage mac_unit_cg.v:
//
//   1. OPERAND ISOLATION: mac_unit_cg.v gates the *output register's*
//      clock, but `mult = a * b` is a combinational multiplier that keeps
//      toggling every time a/b change, REGARDLESS of `en`. That toggling
//      still burns dynamic power even while the design is "disabled".
//      Here, a_iso/b_iso are forced to 0 whenever en=0, so the
//      multiplier's internal combinational logic sees constant inputs
//      and stops toggling too -- not just the register.
//
//   2. FINE-GRAIN, PER-STAGE CLOCK GATING: the design is pipelined
//      (multiply in stage 1, accumulate in stage 2), and EACH stage has
//      its OWN clock-gating cell, gated by that stage's own valid signal.
//      This means stage 2's clock only ungates on cycles where stage 1
//      actually produced a valid product -- e.g. after a single `en=1`
//      followed by `en=0`, stage 1's clock gates off immediately, but
//      stage 2 still needs one more active cycle to drain the pipeline,
//      then also gates off. Coarser (single, block-level) gating cannot
//      express this -- it's an all-or-nothing gate for the whole unit.
//
// Latency: 2 cycles (valid_out is asserted 2 cycles after a request with
// en=1). Throughput: 1 operation/cycle (fully pipelined).
module mac_unit_pipelined_cg #(
    parameter WIDTH = 16
)(
    input  wire               clk,
    input  wire               rst_n,
    input  wire               en,        // request / stage-0 valid-in
    input  wire [WIDTH-1:0]   a,
    input  wire [WIDTH-1:0]   b,
    output reg  [2*WIDTH-1:0] acc,
    output reg                valid_out  // acc updated this cycle
);

    // ---------------- Stage 0: operand isolation + multiply ----------------
    // Isolate operands when idle so the multiplier's combinational logic
    // (a big fan-in tree) doesn't toggle on every unrelated a/b change.
    wire [WIDTH-1:0]   a_iso = en ? a : {WIDTH{1'b0}};
    wire [WIDTH-1:0]   b_iso = en ? b : {WIDTH{1'b0}};
    wire [2*WIDTH-1:0] mult  = a_iso * b_iso;

    // ---------------- Stage 1: pipeline register (product) ----------------
    // FIX (found by the self-checking testbench, see tb_mac_pipelined.sv --
    // 1997/1999 mismatches before this): the control signal `valid_s1`
    // must NOT be clocked by the gated clock it also helps generate.
    // When en=0, gated_clk_s1 never ticks, so a `valid_s1` register
    // living on gated_clk_s1 would freeze at its last value instead of
    // deasserting -- stage 2 then keeps re-consuming a stale product
    // forever. Fix: keep the 1-bit valid/control chain on the ALWAYS-ON
    // clock (negligible power cost either way for 1 bit), and gate ONLY
    // the wide data register (mult_r) whose toggling is actually worth
    // saving power on.
    wire gated_clk_s1;
    clock_gating_cell u_cg_s1 (
        .clk       (clk),
        .en        (en),
        .test_en   (1'b0),
        .gated_clk (gated_clk_s1)
    );

    reg [2*WIDTH-1:0] mult_r;
    reg               valid_s1;

    // Data register: gated (only worth updating -- and only worth the
    // capacitive toggling -- when en=1).
    always @(posedge gated_clk_s1 or negedge rst_n) begin
        if (!rst_n)
            mult_r <= {2*WIDTH{1'b0}};
        else
            mult_r <= mult;
    end

    // Control register: ALWAYS-ON clock, so it correctly tracks en's
    // transitions every cycle, including the deassertion.
    always @(posedge clk or negedge rst_n) begin
        if (!rst_n)
            valid_s1 <= 1'b0;
        else
            valid_s1 <= en;
    end

    // ---------------- Stage 2: accumulate ----------------
    // Gated on valid_s1, NOT on `en` -- this stage's clock must stay
    // ungated one extra cycle after `en` drops, to drain the pipeline.
    wire gated_clk_s2;
    clock_gating_cell u_cg_s2 (
        .clk       (clk),
        .en        (valid_s1),
        .test_en   (1'b0),
        .gated_clk (gated_clk_s2)
    );

    wire [2*WIDTH-1:0] sum = acc + mult_r;

    // Data register: gated.
    always @(posedge gated_clk_s2 or negedge rst_n) begin
        if (!rst_n)
            acc <= {2*WIDTH{1'b0}};
        else if (valid_s1)
            acc <= sum;
    end

    // Control register: ALWAYS-ON clock.
    always @(posedge clk or negedge rst_n) begin
        if (!rst_n)
            valid_out <= 1'b0;
        else
            valid_out <= valid_s1;
    end

endmodule

src/mac_unit_cg.v
// mac_unit_cg.v
// MAC unit WITH explicit clock gating via clock_gating_cell.
// Sequential logic is clocked by gated_clk instead of clk, so the
// register bank does not toggle at all when `en` is low.
module mac_unit_cg #(
    parameter WIDTH = 16
)(
    input  wire               clk,
    input  wire               rst_n,
    input  wire               en,
    input  wire [WIDTH-1:0]   a,
    input  wire [WIDTH-1:0]   b,
    output reg  [2*WIDTH-1:0] acc
);

    wire gated_clk;
    wire [2*WIDTH-1:0] mult;
    wire [2*WIDTH-1:0] sum;

    // Instantiate clock gating cell. Instance is named u_cg — the
    // constraints file below matches it by REF_NAME so DONT_TOUCH
    // still applies no matter what this instance is called.
    clock_gating_cell u_cg (
        .clk       (clk),
        .en        (en),
        .test_en   (1'b0),      // tie low: normal (non-DFT) operation
        .gated_clk (gated_clk)
    );

    // Combinational logic (unclocked, so it isn't affected by gating)
    assign mult = a * b;
    assign sum  = acc + mult;

    // Sequential logic uses the GATED clock
    always @(posedge gated_clk or negedge rst_n) begin
        if (!rst_n)
            acc <= {2*WIDTH{1'b0}};
        else if (en)  // belt-and-braces: acc only updates when en=1 anyway
            acc <= sum;
    end

endmodule

src/mac_unit.v
// mac_unit.v
// Baseline MAC (Multiply-Accumulate) unit WITHOUT clock gating.
// Used as the power/reference baseline against mac_unit_cg.v.
module mac_unit #(
    parameter WIDTH = 16
)(
    input  wire               clk,
    input  wire               rst_n,
    input  wire               en,
    input  wire [WIDTH-1:0]   a,
    input  wire [WIDTH-1:0]   b,
    output reg  [2*WIDTH-1:0] acc
);

    wire [2*WIDTH-1:0] mult;
    wire [2*WIDTH-1:0] sum;

    assign mult = a * b;
    assign sum  = acc + mult;
    // NOTE: this is a finite-width free-running accumulator, so `sum`
    // can wrap on overflow. That's expected/accepted here since this
    // project's purpose is a power/toggle-activity comparison between
    // the gated and ungated versions, not a saturating arithmetic core.

    always @(posedge clk or negedge rst_n) begin
        if (!rst_n)
            acc <= {2*WIDTH{1'b0}};
        else if (en)
            acc <= sum;
    end

endmodule

src/tb_activity_sweep.sv
`timescale 1ns/1ps
// tb_activity_sweep.sv
//
// Drives all THREE MAC variants with the IDENTICAL stimulus stream, at a
// configurable activity factor (`+EN_PROB=<0-100>`), and dumps a VCD.
// Correctness is already proven elsewhere (tb_mac.v, tb_mac_pipelined.sv)
// -- this testbench exists purely to capture real, measurable switching
// activity for the toggle-based Clock Gating Efficiency (CGE) analysis
// in scripts/toggle_cge_analysis.py:
//
//   CGE = 1 - (rising-edge count of the gated clock / rising-edge count
//              of the reference clock) over the same window
//
// which is a direct, tool-independent proxy for the dynamic-power
// savings a real Vivado SAIF/report_power flow would show (fewer clock
// edges reaching the registers behind that gate == less switched
// capacitance == less dynamic power), and one we can actually compute
// and plot right here without needing a Vivado license.
module tb_activity_sweep;

    parameter WIDTH = 16;
    parameter N     = 100;

    int en_prob;
    initial begin
        if (!$value$plusargs("EN_PROB=%d", en_prob))
            en_prob = 50;
    end

    logic               clk, rst_n, en;
    logic [WIDTH-1:0]   a, b;
    logic [2*WIDTH-1:0] acc_baseline, acc_cg, acc_pipe;
    logic               pipe_valid_out;

    mac_unit #(.WIDTH(WIDTH)) u_baseline (
        .clk(clk), .rst_n(rst_n), .en(en), .a(a), .b(b), .acc(acc_baseline)
    );

    mac_unit_cg #(.WIDTH(WIDTH)) u_cg (
        .clk(clk), .rst_n(rst_n), .en(en), .a(a), .b(b), .acc(acc_cg)
    );

    mac_unit_pipelined_cg #(.WIDTH(WIDTH)) u_pipe (
        .clk(clk), .rst_n(rst_n), .en(en), .a(a), .b(b),
        .acc(acc_pipe), .valid_out(pipe_valid_out)
    );

    initial begin clk = 0; forever #5 clk = ~clk; end

    int i;
    initial begin
        rst_n = 0; en = 0; a = 0; b = 0;
        #20 rst_n = 1;

        for (i = 0; i < N; i = i + 1) begin
            @(negedge clk);
            en = ($urandom_range(0, 99) < en_prob);
            a  = $urandom;
            b  = $urandom;
        end

        #50;
        $finish;
    end

    // Full recursive dump -- the post-processing script only looks at
    // clk / gated_clk / gated_clk_s1 / gated_clk_s2 by name, but a full
    // dump keeps this testbench simple and reusable for other signals
    // later without having to touch the dump list.
    initial begin
        $dumpfile("activity_sweep.vcd");
        $dumpvars(0, tb_activity_sweep);
    end

endmodule

tmp_cge_sweep/activity_sweep.vcd
$date
	Wed Sep 09 15:32:39 2026
$end
$version
	Icarus Verilog
$end
$timescale
	1ps
$end
$scope module tb_activity_sweep $end
$var wire 1 ! pipe_valid_out $end
$var wire 32 " acc_pipe [31:0] $end
$var wire 32 # acc_cg [31:0] $end
$var wire 32 $ acc_baseline [31:0] $end
$var parameter 32 % N $end
$var parameter 32 & WIDTH $end
$var reg 16 ' a [15:0] $end
$var reg 16 ( b [15:0] $end
$var reg 1 ) clk $end
$var reg 1 * en $end
$var reg 1 + rst_n $end
$var integer 32 , en_prob [31:0] $end
$var integer 32 - i [31:0] $end
$scope module u_baseline $end
$var wire 16 . a [15:0] $end
$var wire 16 / b [15:0] $end
$var wire 1 ) clk $end
$var wire 1 * en $end
$var wire 1 + rst_n $end
$var wire 32 0 sum [31:0] $end
$var wire 32 1 mult [31:0] $end
$var parameter 32 2 WIDTH $end
$var reg 32 3 acc [31:0] $end
$upscope $end
$scope module u_cg $end
$var wire 16 4 a [15:0] $end
$var wire 16 5 b [15:0] $end
$var wire 1 ) clk $end
$var wire 1 * en $end
$var wire 1 + rst_n $end
$var wire 32 6 sum [31:0] $end
$var wire 32 7 mult [31:0] $end
$var wire 1 8 gated_clk $end
$var parameter 32 9 WIDTH $end
$var reg 32 : acc [31:0] $end
$scope module u_cg $end
$var wire 1 ) clk $end
$var wire 1 * en $end
$var wire 1 8 gated_clk $end
$var wire 1 ; test_en $end
$var reg 1 < en_latch $end
$upscope $end
$upscope $end
$scope module u_pipe $end
$var wire 16 = a [15:0] $end
$var wire 16 > b [15:0] $end
$var wire 1 ) clk $end
$var wire 1 * en $end
$var wire 1 + rst_n $end
$var wire 32 ? sum [31:0] $end
$var wire 32 @ mult [31:0] $end
$var wire 1 A gated_clk_s2 $end
$var wire 1 B gated_clk_s1 $end
$var wire 16 C b_iso [15:0] $end
$var wire 16 D a_iso [15:0] $end
$var parameter 32 E WIDTH $end
$var reg 32 F acc [31:0] $end
$var reg 32 G mult_r [31:0] $end
$var reg 1 ! valid_out $end
$var reg 1 H valid_s1 $end
$scope module u_cg_s1 $end
$var wire 1 ) clk $end
$var wire 1 * en $end
$var wire 1 B gated_clk $end
$var wire 1 I test_en $end
$var reg 1 J en_latch $end
$upscope $end
$scope module u_cg_s2 $end
$var wire 1 ) clk $end
$var wire 1 H en $end
$var wire 1 A gated_clk $end
$var wire 1 K test_en $end
$var reg 1 L en_latch $end
$upscope $end
$upscope $end
$upscope $end
$enddefinitions $end
$comment Show the parameter values. $end
$dumpall
b10000 E
b10000 9
b10000 2
b10000 &
b101110111000 %
$end
#0
$dumpvars
0L
0K
0J
0I
0H
b0 G
b0 F
b0 D
b0 C
0B
0A
b0 @
b0 ?
b0 >
b0 =
0<
0;
b0 :
08
b0 7
b0 6
b0 5
b0 4
b0 3
b0 1
b0 0
b0 /
b0 .
b0 -
b1100100 ,
0+
0*
0)
b0 (
b0 '
b0 $
b0 #
b0 "
0!
$end
#5000
1)
#10000
0)
#15000
1)
#20000
b1001111000000110010100010001001 @
b101111010000001 D
b1101011000001001 C
1<
1J
b1 -
b1001111000000110010100010001001 0
b1001111000000110010100010001001 1
b1001111000000110010100010001001 6
b1001111000000110010100010001001 7
b1101011000001001 (
b1101011000001001 /
b1101011000001001 5
b1101011000001001 >
b101111010000001 '
b101111010000001 .
b101111010000001 4
b101111010000001 =
1*
0)
1+
#25000
b10011110000001100101000100010010 6
b1001111000000110010100010001001 #
b1001111000000110010100010001001 :
b1001111000000110010100010001001 ?
b1001111000000110010100010001001 G
1H
b10011110000001100101000100010010 0
b1001111000000110010100010001001 $
b1001111000000110010100010001001 3
18
1B
1)
#30000
b1001100110001101 C
b1001001110011101000101100101001 @
b111101100001101 D
08
0B
1L
b10 -
b1001100110001101 (
b1001100110001101 /
b1001100110001101 5
b1001100110001101 >
b10011000110100011011001110110010 0
b1001001110011101000101100101001 1
b10011000110100011011001110110010 6
b1001001110011101000101100101001 7
b111101100001101 '
b111101100001101 .
b111101100001101 4
b111101100001101 =
0)
#35000
b11100010101000000011111011011011 6
b10011000110100011011001110110010 #
b10011000110100011011001110110010 :
b1001001110011101000101100101001 G
b10011000110100011011001110110010 ?
b1001111000000110010100010001001 "
b1001111000000110010100010001001 F
b11100010101000000011111011011011 0
b10011000110100011011001110110010 $
b10011000110100011011001110110010 3
1!
18
1B
1A
1)
#40000
b1110001100000001 C
b1001000110001100100100000010010 @
b101001000010010 D
08
0B
0A
b11 -
b1110001100000001 (
b1110001100000001 /
b1110001100000001 5
b1110001100000001 >
b11100001100101111111101111000100 0
b1001000110001100100100000010010 1
b11100001100101111111101111000100 6
b1001000110001100100100000010010 7
b101001000010010 '
b101001000010010 .
b101001000010010 4
b101001000010010 =
0)
#45000
b101010010111100100001111010110 6
b11100001100101111111101111000100 #
b11100001100101111111101111000100 :
b1001000110001100100100000010010 G
b11100001100101111111101111000100 ?
b10011000110100011011001110110010 "
b10011000110100011011001110110010 F
b101010010111100100001111010110 0
b11100001100101111111101111000100 $
b11100001100101111111101111000100 3
18
1B
1A
1)
#50000
b1100110100111101 C
b11000001100101010000011100011110 @
b1111000101110110 D
08
0B
0A
b100 -
b1100110100111101 (
b1100110100111101 /
b1100110100111101 5
b1100110100111101 >
b10100011001011010000001011100010 0
b11000001100101010000011100011110 1
b10100011001011010000001011100010 6
b11000001100101010000011100011110 7
b1111000101110110 '
b1111000101110110 .
b1111000101110110 4
b1111000101110110 =
0)
#55000
b1100100110000100000101000000000 6
b10100011001011010000001011100010 #
b10100011001011010000001011100010 :
b11000001100101010000011100011110 G
b10100011001011010000001011100010 ?
b11100001100101111111101111000100 "
b11100001100101111111101111000100 F
b1100100110000100000101000000000 0
b10100011001011010000001011100010 $
b10100011001011010000001011100010 3
18
1B
1A
1)
#60000
b1110100111111001 C
b11100010001111110011001100101100 @
b1111011110001100 D
08
0B
0A
b101 -
b1110100111111001 (
b1110100111111001 /
b1110100111111001 5
b1110100111111001 >
b10000101011011000011011000001110 0
b11100010001111110011001100101100 1
b10000101011011000011011000001110 6
b11100010001111110011001100101100 7
b1111011110001100 '
b1111011110001100 .
b1111011110001100 4
b1111011110001100 =
0)
#65000
b1100111101010110110100100111010 6
b10000101011011000011011000001110 #
b10000101011011000011011000001110 :
b11100010001111110011001100101100 G
b10000101011011000011011000001110 ?
b10100011001011010000001011100010 "
b10100011001011010000001011100010 F
b1100111101010110110100100111010 0
b10000101011011000011011000001110 $
b10000101011011000011011000001110 3
18
1B
1A
1)
#70000
b1101001010101010 C
b1101101010000011100010011010010 @
b1000010011000101 D
08
0B
0A
b110 -
b1101001010101010 (
b1101001010101010 /
b1101001010101010 5
b1101001010101010 >
b11110010101011011111101011100000 0
b1101101010000011100010011010010 1
b11110010101011011111101011100000 6
b1101101010000011100010011010010 7
b1000010011000101 '
b1000010011000101 .
b1000010011000101 4
b1000010011000101 =
0)
#75000
b1011111111011111011111110110010 6
b11110010101011011111101011100000 #
b11110010101011011111101011100000 :
b1101101010000011100010011010010 G
b11110010101011011111101011100000 ?
b10000101011011000011011000001110 "
b10000101011011000011011000001110 F
b1011111111011111011111110110010 0
b11110010101011011111101011100000 $
b11110010101011011111101011100000 3
18
1B
1A
1)
#80000
b1101011000010010 C
b1011111101101111000011001011110 @
b111001001110111 D
08
0B
0A
b111 -
b1101011000010010 (
b1101011000010010 /
b1101011000010010 5
b1101011000010010 >
b1010010011001011000000100111110 0
b1011111101101111000011001011110 1
b1010010011001011000000100111110 6
b1011111101101111000011001011110 7
b111001001110111 '
b111001001110111 .
b111001001110111 4
b111001001110111 =
0)
#85000
b10110010000111010000011110011100 6
b1010010011001011000000100111110 #
b1010010011001011000000100111110 :
b1011111101101111000011001011110 G
b1010010011001011000000100111110 ?
b11110010101011011111101011100000 "
b11110010101011011111101011100000 F
b10110010000111010000011110011100 0
b1010010011001011000000100111110 $
b1010010011001011000000100111110 3
18
1B
1A
1)
#90000
b1001011011001110 C
b111110011010010000110010111100 @
b110100111110010 D
08
0B
0A
b1000 -
b1001011011001110 (
b1001011011001110 /
b1001011011001110 5
b1001011011001110 >
b10010000110011101000110111111010 0
b111110011010010000110010111100 1
b10010000110011101000110111111010 6
b111110011010010000110010111100 7
b110100111110010 '
b110100111110010 .
b110100111110010 4
b110100111110010 =
0)
#95000
b11001111001101111001101010110110 6
b10010000110011101000110111111010 #
b10010000110011101000110111111010 :
b111110011010010000110010111100 G
b10010000110011101000110111111010 ?
b1010010011001011000000100111110 "
b1010010011001011000000100111110 F
b11001111001101111001101010110110 0
b10010000110011101000110111111010 $
b10010000110011101000110111111010 3
18
1B
1A
1)
#100000
b100100101011100 C
b10110100100100111101111001100 @
b100111011000101 D
08
0B
0A
b1001 -
b100100101011100 (
b100100101011100 /
b100100101011100 5
b100100101011100 >
b10100111011000010000100111000110 0
b10110100100100111101111001100 1
b10100111011000010000100111000110 6
b10110100100100111101111001100 7
b100111011000101 '
b100111011000101 .
b100111011000101 4
b100111011000101 =
0)
#105000
b10111101111100111000010110010010 6
b10100111011000010000100111000110 #
b10100111011000010000100111000110 :
b10110100100100111101111001100 G
b10100111011000010000100111000110 ?
b10010000110011101000110111111010 "
b10010000110011101000110111111010 F
b10111101111100111000010110010010 0
b10100111011000010000100111000110 $
b10100111011000010000100111000110 3
18
1B
1A
1)
#110000
b10011001100101 C
b1101001110010111011111000001 @
b101100000101101 D
08
0B
0A
b1010 -
b10011001100101 (
b10011001100101 /
b10011001100101 5
b10011001100101 >
b10110100100110101000000110000111 0
b1101001110010111011111000001 1
b10110100100110101000000110000111 6
b1101001110010111011111000001 7
b101100000101101 '
b101100000101101 .
b101100000101101 4
b101100000101101 =
0)
#115000
b11000001110100111111100101001000 6
b10110100100110101000000110000111 #
b10110100100110101000000110000111 :
b1101001110010111011111000001 G
b10110100100110101000000110000111 ?
b10100111011000010000100111000110 "
b10100111011000010000100111000110 F
b11000001110100111111100101001000 0
b10110100100110101000000110000111 $
b10110100100110101000000110000111 3
18
1B
1A
1)
#120000
b10001010000000 C
b10010001100101101100100000000 @
b1000011100001010 D
08
0B
0A
b1011 -
b10001010000000 (
b10001010000000 /
b10001010000000 5
b10001010000000 >
b11000110110011010101101010000111 0
b10010001100101101100100000000 1
b11000110110011010101101010000111 6
b10010001100101101100100000000 7
b1000011100001010 '
b1000011100001010 .
b1000011100001010 4
b1000011100001010 =
0)
#125000
b11011001000000000011001110000111 6
b11000110110011010101101010000111 #
b11000110110011010101101010000111 :
b10010001100101101100100000000 G
b11000110110011010101101010000111 ?
b10110100100110101000000110000111 "
b10110100100110101000000110000111 F
b11011001000000000011001110000111 0
b11000110110011010101101010000111 $
b11000110110011010101101010000111 3
18
1B
1A
1)
#130000
b1100110010011101 C
b110111101011100011000101000010 @
b100010110101010 D
08
0B
0A
b1100 -
b1100110010011101 (
b1100110010011101 /
b1100110010011101 5
b1100110010011101 >
b11111110011110111000101111001001 0
b110111101011100011000101000010 1
b11111110011110111000101111001001 6
b110111101011100011000101000010 7
b100010110101010 '
b100010110101010 .
b100010110101010 4
b100010110101010 =
0)
#135000
b110110001010011011110100001011 6
b11111110011110111000101111001001 #
b11111110011110111000101111001001 :
b110111101011100011000101000010 G
b11111110011110111000101111001001 ?
b11000110110011010101101010000111 "
b11000110110011010101101010000111 F
b110110001010011011110100001011 0
b11111110011110111000101111001001 $
b11111110011110111000101111001001 3
18
1B
1A
1)
#140000
b11100000001101 C
b101000010011011000000011110111 @
b1011100000010011 D
08
0B
0A
b1101 -
b11100000001101 (
b11100000001101 /
b11100000001101 5
b11100000001101 >
b100110110010010000110011000000 0
b101000010011011000000011110111 1
b100110110010010000110011000000 6
b101000010011011000000011110111 7
b1011100000010011 '
b1011100000010011 .
b1011100000010011 4
b1011100000010011 =
0)
#145000
b1001111000101101000110110110111 6
b100110110010010000110011000000 #
b100110110010010000110011000000 :
b101000010011011000000011110111 G
b100110110010010000110011000000 ?
b11111110011110111000101111001001 "
b11111110011110111000101111001001 F
b1001111000101101000110110110111 0
b100110110010010000110011000000 $
b100110110010010000110011000000 3
18
1B
1A
1)
#150000
b10101011010101 C
b100101000010111100100000000111 @
b1101110101101011 D
08
0B
0A
b1110 -
b10101011010101 (
b10101011010101 /
b10101011010101 5
b10101011010101 >
b1001011110101001101010011000111 0
b100101000010111100100000000111 1
b1001011110101001101010011000111 6
b100101000010111100100000000111 7
b1101110101101011 '
b1101110101101011 .
b1101110101101011 4
b1101110101101011 =
0)
#155000
b1110000111000001001110011001110 6
b1001011110101001101010011000111 #
b1001011110101001101010011000111 :
b100101000010111100100000000111 G
b1001011110101001101010011000111 ?
b100110110010010000110011000000 "
b100110110010010000110011000000 F
b1110000111000001001110011001110 0
b1001011110101001101010011000111 $
b1001011110101001101010011000111 3
18
1B
1A
1)
#160000
b1110100100011101 C
b111001000100110111011110110110 @
b11111010101110 D
08
0B
0A
b1111 -
b1110100100011101 (
b1110100100011101 /
b1110100100011101 5
b1110100100011101 >
b10000100111010000100110001111101 0
b111001000100110111011110110110 1
b10000100111010000100110001111101 6
b111001000100110111011110110110 7
b11111010101110 '
b11111010101110 .
b11111010101110 4
b11111010101110 =
0)
#165000
b10111101111110111100010000110011 6
b10000100111010000100110001111101 #
b10000100111010000100110001111101 :
b111001000100110111011110110110 G
b10000100111010000100110001111101 ?
b1001011110101001101010011000111 "
b1001011110101001101010011000111 F
b10111101111110111100010000110011 0
b10000100111010000100110001111101 $
b10000100111010000100110001111101 3
18
1B
1A
1)
#170000
b110010100001010 C
b11100110111011010101001011110 @
b100100100100011 D
08
0B
0A
b10000 -
b110010100001010 (
b110010100001010 /
b110010100001010 5
b110010100001010 >
b10100001110001011111011011011011 0
b11100110111011010101001011110 1
b10100001110001011111011011011011 6
b11100110111011010101001011110 7
b100100100100011 '
b100100100100011 .
b100100100100011 4
b100100100100011 =
0)
#175000
b10111110101000111010000100111001 6
b10100001110001011111011011011011 #
b10100001110001011111011011011011 :
b11100110111011010101001011110 G
b10100001110001011111011011011011 ?
b10000100111010000100110001111101 "
b10000100111010000100110001111101 F
b10111110101000111010000100111001 0
b10100001110001011111011011011011 $
b10100001110001011111011011011011 3
18
1B
1A
1)
#180000
b1011110111110010 C
b111000100100000101110010111000 @
b100110000111100 D
08
0B
0A
b10001 -
b1011110111110010 (
b1011110111110010 /
b1011110111110010 5
b1011110111110010 >
b11011010010101100101001110010011 0
b111000100100000101110010111000 1
b11011010010101100101001110010011 6
b111000100100000101110010111000 7
b100110000111100 '
b100110000111100 .
b100110000111100 4
b100110000111100 =
0)
#185000
b10010111001101011000001001011 6
b11011010010101100101001110010011 #
b11011010010101100101001110010011 :
b111000100100000101110010111000 G
b11011010010101100101001110010011 ?
b10100001110001011111011011011011 "
b10100001110001011111011011011011 F
b10010111001101011000001001011 0
b11011010010101100101001110010011 $
b11011010010101100101001110010011 3
18
1B
1A
1)
#190000
b11010011011000 C
b100101000000000111001011011000 @
b1011001101000001 D
08
0B
0A
b10010 -
b11010011011000 (
b11010011011000 /
b11010011011000 5
b11010011011000 >
b11111111010101101100011001101011 0
b100101000000000111001011011000 1
b11111111010101101100011001101011 6
b100101000000000111001011011000 7
b1011001101000001 '
b1011001101000001 .
b1011001101000001 4
b1011001101000001 =
0)
#195000
b100100010101110011100101000011 6
b11111111010101101100011001101011 #
b11111111010101101100011001101011 :
b100101000000000111001011011000 G
b11111111010101101100011001101011 ?
b11011010010101100101001110010011 "
b11011010010101100101001110010011 F
b100100010101110011100101000011 0
b11111111010101101100011001101011 $
b11111111010101101100011001101011 3
18
1B
1A
1)
#200000
b110111101011 C
b1000000011111100011000011 @
b1001010001001 D
08
0B
0A
b10011 -
b110111101011 (
b110111101011 /
b110111101011 5
b110111101011 >
b10110001011111100101110 0
b1000000011111100011000011 1
b10110001011111100101110 6
b1000000011111100011000011 7
b1001010001001 '
b1001010001001 .
b1001010001001 4
b1001010001001 =
0)
#205000
b1010110101011011111110001 6
b10110001011111100101110 #
b10110001011111100101110 :
b1000000011111100011000011 G
b10110001011111100101110 ?
b11111111010101101100011001101011 "
b11111111010101101100011001101011 F
b1010110101011011111110001 0
b10110001011111100101110 $
b10110001011111100101110 3
18
1B
1A
1)
#210000
b1001110101110 C
b10011001100110111011010010100 @
b1111100111000110 D
08
0B
0A
b10100 -
b1001110101110 (
b1001110101110 /
b1001110101110 5
b1001110101110 >
b10011100011000011010111000010 0
b10011001100110111011010010100 1
b10011100011000011010111000010 6
b10011001100110111011010010100 7
b1111100111000110 '
b1111100111000110 .
b1111100111000110 4
b1111100111000110 =
0)
#215000
b100110101111111010110001010110 6
b10011100011000011010111000010 #
b10011100011000011010111000010 :
b10011001100110111011010010100 G
b10011100011000011010111000010 ?
b10110001011111100101110 "
b10110001011111100101110 F
b100110101111111010110001010110 0
b10011100011000011010111000010 $
b10011100011000011010111000010 3
18
1B
1A
1)
#220000
b1001101000001011 C
b10000101000101001100010011001110 @
b1101110100101010 D
08
0B
0A
b10101 -
b1001101000001011 (
b1001101000001011 /
b1001101000001011 5
b1001101000001011 >
b10011000101000001111101010010000 0
b10000101000101001100010011001110 1
b10011000101000001111101010010000 6
b10000101000101001100010011001110 7
b1101110100101010 '
b1101110100101010 .
b1101110100101010 4
b1101110100101010 =
0)
#225000
b11101101101011011111101011110 6
b10011000101000001111101010010000 #
b10011000101000001111101010010000 :
b10000101000101001100010011001110 G
b10011000101000001111101010010000 ?
b10011100011000011010111000010 "
b10011100011000011010111000010 F
b11101101101011011111101011110 0
b10011000101000001111101010010000 $
b10011000101000001111101010010000 3
18
1B
1A
1)
#230000
b101010101001111 C
b10101110101010110000100001011 @
b100000110000101 D
08
0B
0A
b10110 -
b101010101001111 (
b101010101001111 /
b101010101001111 5
b101010101001111 >
b10101110011101100101101110011011 0
b10101110101010110000100001011 1
b10101110011101100101101110011011 6
b10101110101010110000100001011 7
b100000110000101 '
b100000110000101 .
b100000110000101 4
b100000110000101 =
0)
#235000
b11000100010010111011110010100110 6
b10101110011101100101101110011011 #
b10101110011101100101101110011011 :
b10101110101010110000100001011 G
b10101110011101100101101110011011 ?
b10011000101000001111101010010000 "
b10011000101000001111101010010000 F
b11000100010010111011110010100110 0
b10101110011101100101101110011011 $
b10101110011101100101101110011011 3
18
1B
1A
1)
#240000
b11001001111110 C
b1010000110101000101010001100 @
b11001100111010 D
08
0B
0A
b10111 -
b11001001111110 (
b11001001111110 /
b11001001111110 5
b11001001111110 >
b10111000100100001110011000100111 0
b1010000110101000101010001100 1
b10111000100100001110011000100111 6
b1010000110101000101010001100 7
b11001100111010 '
b11001100111010 .
b11001100111010 4
b11001100111010 =
0)
#245000
b11000010101010110111000010110011 6
b10111000100100001110011000100111 #
b10111000100100001110011000100111 :
b1010000110101000101010001100 G
b10111000100100001110011000100111 ?
b10101110011101100101101110011011 "
b10101110011101100101101110011011 F
b11000010101010110111000010110011 0
b10111000100100001110011000100111 $
b10111000100100001110011000100111 3
18
1B
1A
1)
#250000
b100101111011001 C
b101110001100111100101001001001 @
b1001101111110001 D
08
0B
0A
b11000 -
b100101111011001 (
b100101111011001 /
b100101111011001 5
b100101111011001 >
b11100110110001001011000001110000 0
b101110001100111100101001001001 1
b11100110110001001011000001110000 6
b101110001100111100101001001001 7
b1001101111110001 '
b1001101111110001 .
b1001101111110001 4
b1001101111110001 =
0)
#255000
b10100111110000111101010111001 6
b11100110110001001011000001110000 #
b11100110110001001011000001110000 :
b101110001100111100101001001001 G
b11100110110001001011000001110000 ?
b10111000100100001110011000100111 "
b10111000100100001110011000100111 F
b10100111110000111101010111001 0
b11100110110001001011000001110000 $
b11100110110001001011000001110000 3
18
1B
1A
1)
#260000
b101010110011111 C
b1010100000011000101000000110100 @
b1111101101001100 D
08
0B
0A
b11001 -
b101010110011111 (
b101010110011111 /
b101010110011111 5
b101010110011111 >
b111010110100010000000010100100 0
b1010100000011000101000000110100 1
b111010110100010000000010100100 6
b1010100000011000101000000110100 7
b1111101101001100 '
b1111101101001100 .
b1111101101001100 4
b1111101101001100 =
0)
#265000
b10001110110111010101000011011000 6
b111010110100010000000010100100 #
b111010110100010000000010100100 :
b1010100000011000101000000110100 G
b111010110100010000000010100100 ?
b11100110110001001011000001110000 "
b11100110110001001011000001110000 F
b10001110110111010101000011011000 0
b111010110100010000000010100100 $
b111010110100010000000010100100 3
18
1B
1A
1)
#270000
b110000010110111 C
b1000000001101101000000001001000 @
b1010100111111000 D
08
0B
0A
b11010 -
b110000010110111 (
b110000010110111 /
b110000010110111 5
b110000010110111 >
b1111011000001111000000011101100 0
b1000000001101101000000001001000 1
b1111011000001111000000011101100 6
b1000000001101101000000001001000 7
b1010100111111000 '
b1010100111111000 .
b1010100111111000 4
b1010100111111000 =
0)
